FunctionalX/__init__.py
FunctionalX/src/__init__.py
FunctionalX/src/lists/__init__.py
FunctionalX/src/lists/_cart2.py
FunctionalX/src/lists/_cart_append.py
FunctionalX/src/lists/_cartn.py
FunctionalX/src/lists/_dict2list.py
FunctionalX/src/lists/_head.py
FunctionalX/src/lists/_tail.py
FunctionalX/src/lists/cart2.py
FunctionalX/src/lists/cart_append.py
FunctionalX/src/lists/cartn.py
FunctionalX/src/lists/dict2list.py
FunctionalX/src/lists/others.py
FunctionalX/tests/__init__.py
FunctionalX/tests/_dashed_line.py
FunctionalX/tests/list/__init__.py
FunctionalX/tests/list/cart2/__init__.py
FunctionalX/tests/list/cart2/test_1.py
FunctionalX/tests/lists/__init__.py
FunctionalX/tests/lists/cart2/__init__.py
FunctionalX/tests/lists/cart2/test_1.py
FunctionalX/tests/lists/cart_append/__init__.py
FunctionalX/tests/lists/cart_append/test_1.py
FunctionalX/tests/lists/cartn/__init__.py
FunctionalX/tests/lists/cartn/test_1.py
FunctionalX/tests/lists/dict2list/__init__.py
FunctionalX/tests/lists/dict2list/test_1.py
FunctionalX/tests/lists/head/__init__.py
FunctionalX/tests/lists/head/test_1.py
FunctionalX/tests/lists/head/test_2.py
FunctionalX/tests/lists/tail/__init__.py
FunctionalX/tests/lists/tail/test_1.py
FunctionalX/tests/lists/tail/test_2.py
FunctionalX/tests/lists/tail/test_3.py
FunctionalX-0.0.3.dist-info/DESCRIPTION.rst
FunctionalX-0.0.3.dist-info/METADATA
FunctionalX-0.0.3.dist-info/RECORD
FunctionalX-0.0.3.dist-info/WHEEL
FunctionalX-0.0.3.dist-info/metadata.json
FunctionalX-0.0.3.dist-info/top_level.txt
